odoo10_addon_hr_expense_sequence-10.0.1.0.0.99.dev9-py2.7-nspkg.pth
odoo/addons/hr_expense_sequence/README.rst
odoo/addons/hr_expense_sequence/__init__.py
odoo/addons/hr_expense_sequence/__manifest__.py
odoo/addons/hr_expense_sequence/data/hr_expense_data.xml
odoo/addons/hr_expense_sequence/i18n/cs_CZ.po
odoo/addons/hr_expense_sequence/i18n/de.po
odoo/addons/hr_expense_sequence/i18n/es.po
odoo/addons/hr_expense_sequence/i18n/fi.po
odoo/addons/hr_expense_sequence/i18n/fr.po
odoo/addons/hr_expense_sequence/i18n/hr.po
odoo/addons/hr_expense_sequence/i18n/hr_expense_sequence.pot
odoo/addons/hr_expense_sequence/i18n/it.po
odoo/addons/hr_expense_sequence/i18n/nl_NL.po
odoo/addons/hr_expense_sequence/i18n/pt_BR.po
odoo/addons/hr_expense_sequence/i18n/sl.po
odoo/addons/hr_expense_sequence/models/__init__.py
odoo/addons/hr_expense_sequence/models/hr_expense_sheet.py
odoo/addons/hr_expense_sequence/report/report_expense_sheet.xml
odoo/addons/hr_expense_sequence/static/description/icon.png
odoo/addons/hr_expense_sequence/views/hr_expense_expense_view.xml
odoo10_addon_hr_expense_sequence-10.0.1.0.0.99.dev9.dist-info/METADATA
odoo10_addon_hr_expense_sequence-10.0.1.0.0.99.dev9.dist-info/RECORD
odoo10_addon_hr_expense_sequence-10.0.1.0.0.99.dev9.dist-info/WHEEL
odoo10_addon_hr_expense_sequence-10.0.1.0.0.99.dev9.dist-info/namespace_packages.txt
odoo10_addon_hr_expense_sequence-10.0.1.0.0.99.dev9.dist-info/top_level.txt
